<?xml version="1.0" encoding="utf-8"?>
<changelogs>

    <changelog>
        <element>com_devartgallery</element>
        <type>component</type>
        <version>1.0.11</version>

        <addition>
            <item>Added thumbnail cache system for improved frontend gallery performance</item>
            <item>Added dedicated thumbnail folders per gallery</item>
            <item>Added per-gallery thumbnail width and height settings</item>
            <item>Added global default thumbnail settings for newly created galleries</item>
            <item>Added thumbnail generation during new gallery photo upload workflow</item>
            <item>Added on-demand thumbnail generation for existing Active galleries</item>
            <item>Added on-demand thumbnail generation for existing Legacy galleries</item>
            <item>Added automatic missing thumbnail regeneration support</item>
            <item>Added thumbnail cache versioning based on gallery thumbnail settings</item>
            <item>Added thumbnail retention and cleanup settings</item>
        </addition>

        <change>
            <item>Improved gallery grid performance by serving optimized thumbnails instead of larger gallery images</item>
            <item>Improved bandwidth usage for image-heavy gallery pages</item>
            <item>Improved scalability for large Joomla gallery installations</item>
            <item>Improved Cloudflare and CDN friendliness for gallery frontend rendering</item>
            <item>Improved filesystem organization by separating original gallery images from generated thumbnails</item>
            <item>Improved self-healing behavior when thumbnail files are missing</item>
            <item>Existing Active and Legacy galleries now build thumbnail cache progressively only when requested on the frontend</item>
            <item>New gallery uploads now create thumbnails during save/upload operations</item>
        </change>

        <note>
            <item>Performance-focused release for high-traffic and image-heavy Joomla websites</item>
            <item>Existing galleries are not processed during installation or upgrade</item>
            <item>No mass thumbnail generation is performed during update</item>
            <item>Thumbnail cache is created progressively as galleries are accessed</item>
            <item>No database schema changes introduced</item>
            <item>No migration process required</item>
            <item>Recommended update for all DevArt Gallery installations</item>
        </note>
    </changelog>

    <changelog>
        <element>com_devartgallery</element>
        <type>component</type>
        <version>1.0.10</version>

        <fix>
            <item>Fixed critical Joomla 6 administrator fatal error in New Gallery workflow caused by incorrect model architecture</item>
            <item>Fixed New Gallery model to use proper Joomla AdminModel form workflow</item>
            <item>Fixed broken gallery save workflow for newly created galleries</item>
            <item>Fixed broken administrator Back / Cancel toolbar behavior in New Gallery view</item>
            <item>Fixed missing administrator language string COM_DEVARTGALLERY_ALIAS</item>
        </fix>

        <change>
            <item>Improved Joomla 6 administrator form compatibility for gallery creation workflow</item>
            <item>Improved production stability for administrator gallery management</item>
            <item>Improved reliability of New Gallery create/save operations</item>
        </change>

        <note>
            <item>Critical production hotfix release</item>
            <item>Recommended update for all DevArt Gallery v1.0.9 installations</item>
            <item>No frontend behavior changes or feature modifications in this release</item>
        </note>
    </changelog>

    <changelog>
        <element>com_devartgallery</element>
        <type>component</type>
        <version>1.0.9</version>

        <fix>
            <item>Fixed component configuration parameter handling when Joomla stores component params in nested JSON format</item>
            <item>Fixed Dashboard showing fallback or incorrect gallery paths instead of configured values</item>
            <item>Fixed Legacy Archive Directory display inconsistencies in administrator dashboard</item>
            <item>Fixed Active Gallery Directory display inconsistencies in administrator dashboard</item>
            <item>Fixed Legacy Index rebuild using incorrect directory values in specific installations</item>
            <item>Fixed Active Index rebuild using incorrect directory values in specific installations</item>
            <item>Fixed indexing behavior when configuration values were correctly saved but incorrectly read by internal component logic</item>
        </fix>

        <change>
            <item>Improved compatibility with different Joomla component parameter storage behaviors</item>
            <item>Improved dashboard configuration accuracy across installations</item>
            <item>Improved gallery indexing reliability for production environments</item>
            <item>Improved migration safety for legacy gallery deployments</item>
            <item>Improved internal configuration loading consistency</item>
        </change>

        <note>
            <item>This release focuses on configuration reliability, indexing stability and production consistency</item>
            <item>Recommended update for all previous DevArt Gallery releases</item>
        </note>
    </changelog>

    <changelog>
        <element>com_devartgallery</element>
        <type>component</type>
        <version>1.0.4</version>

        <fix>
            <item>Fixed Legacy Archive Directory custom path handling when changed from default values</item>
            <item>Fixed Active Gallery Directory custom path handling when changed from default values</item>
            <item>Fixed dashboard directory cards showing incorrect default paths after configuration changes</item>
            <item>Fixed Legacy Index rebuild ignoring custom Legacy Archive Directory settings</item>
            <item>Fixed Active Index rebuild ignoring custom Active Gallery Directory settings</item>
            <item>Fixed legacy indexing conflicts when Legacy Archive Directory includes the Active Gallery Directory</item>
        </fix>

        <change>
            <item>Improved path normalization and component parameter loading consistency</item>
            <item>Improved migration safety when legacy galleries are indexed from broader directories</item>
            <item>Improved dashboard accuracy for custom gallery path deployments</item>
            <item>Improved Joomla Update metadata consistency for production releases</item>
        </change>

        <note>
            <item>This release focused on custom path handling, indexing reliability and migration safety</item>
            <item>Recommended update for users of earlier initial releases</item>
        </note>
    </changelog>

    <changelog>
        <element>com_devartgallery</element>
        <type>component</type>
        <version>1.0.0</version>

        <addition>
            <item>Added full Joomla 6 native DevArt Image Gallery component with modern MVC architecture</item>
            <item>Added active managed gallery system</item>
            <item>Added legacy gallery indexing with read-only compatibility support</item>
            <item>Added portable path-based shortcode support for legacy and active galleries</item>
            <item>Added frontend gallery display module</item>
            <item>Added content plugin for article gallery rendering</item>
            <item>Added editor button for easy gallery shortcode insertion</item>
            <item>Added popup image viewer support</item>
            <item>Added responsive frontend gallery layouts</item>
            <item>Added Normal Grid and Masonry frontend display modes</item>
            <item>Added gallery management interface</item>
            <item>Added Manage Photos interface with pagination</item>
            <item>Added Scan Existing Photos support</item>
            <item>Added automatic image indexing system</item>
            <item>Added support for JPG, PNG and WEBP image uploads</item>
            <item>Added automatic image optimization workflow</item>
            <item>Added strict filename sanitization policy</item>
            <item>Added optional watermark support per gallery</item>
            <item>Added Joomla menu item integration for direct gallery frontend pages</item>
            <item>Added Joomla ACL permissions support</item>
            <item>Added Keep Data on Uninstall option</item>
            <item>Added GitHub-based Joomla update server support</item>
        </addition>

        <change>
            <item>Gallery architecture designed specifically for Joomla 6 and PHP 8.2+</item>
            <item>Legacy gallery compatibility implemented without modifying historical gallery folders</item>
            <item>Frontend rendering kept lightweight to minimize template conflicts</item>
            <item>CSS and JavaScript namespaced for safer third-party compatibility</item>
            <item>Manage Photos optimized with pagination for larger galleries</item>
            <item>Gallery indexing optimized for controlled batch operations</item>
            <item>Modern service provider and MVCComponent architecture used throughout</item>
        </change>

        <security>
            <item>Added SQL injection protection using Joomla database APIs and parameterized queries</item>
            <item>Added XSS protection through proper output escaping</item>
            <item>Added CSRF protection for administrator actions</item>
            <item>Added path traversal protection for filesystem operations</item>
            <item>Added strict filename validation for safer uploads</item>
            <item>Added ACL enforcement for administrator operations</item>
        </security>

        <note>
            <item>Initial public release of DevArt Image Gallery for Joomla 6</item>
            <item>Designed for editorial, news and high-traffic Joomla websites</item>
            <item>Always test on a staging environment before production deployment</item>
        </note>
    </changelog>

</changelogs>
